{
  "$schema": "https://developer.microsoft.com/json-schemas/fabric/item/report/definition/visualContainer/2.8.0/schema.json",
  "name": "55d7a7268b14f76e90ff",
  "position": {
    "x": 550.14662756598239,
    "y": 178.40469208211144,
    "z": 1000,
    "height": 334.80351906158359,
    "width": 779.63636363636363,
    "tabOrder": 5000
  },
  "visual": {
    "visualType": "pivotTable",
    "query": {
      "queryState": {
        "Columns": {
          "projections": [
            {
              "field": {
                "Column": {
                  "Expression": {
                    "SourceRef": {
                      "Entity": "D_Date"
                    }
                  },
                  "Property": "yearMonth"
                }
              },
              "queryRef": "DIM_Danh mục_Ngày.yearMonth",
              "nativeQueryRef": "Năm/Tháng",
              "active": true,
              "displayName": "Năm/Tháng"
            }
          ]
        },
        "Rows": {
          "projections": [
            {
              "field": {
                "Column": {
                  "Expression": {
                    "SourceRef": {
                      "Entity": "D_Region"
                    }
                  },
                  "Property": "Miền"
                }
              },
              "queryRef": "D_Region.Miền",
              "nativeQueryRef": "Miền",
              "active": true,
              "displayName": "Miền"
            },
            {
              "field": {
                "Column": {
                  "Expression": {
                    "SourceRef": {
                      "Entity": "F_Ycdc"
                    }
                  },
                  "Property": "Khu vực"
                }
              },
              "queryRef": "F_Ycdc.Khu vực",
              "nativeQueryRef": "Khu vực",
              "active": true,
              "displayName": "Khu vực"
            },
            {
              "field": {
                "Column": {
                  "Expression": {
                    "SourceRef": {
                      "Entity": "F_Ycdc"
                    }
                  },
                  "Property": "DC_Type"
                }
              },
              "queryRef": "F_Ycdc.DC_Type",
              "nativeQueryRef": "DC Type",
              "active": true,
              "displayName": "DC Type"
            }
          ],
          "fieldParameters": [
            {
              "parameterExpr": {
                "Column": {
                  "Expression": {
                    "SourceRef": {
                      "Entity": "Parameter"
                    }
                  },
                  "Property": "Parameter"
                }
              },
              "index": 0,
              "length": 3
            }
          ]
        },
        "Values": {
          "projections": [
            {
              "field": {
                "Measure": {
                  "Expression": {
                    "SourceRef": {
                      "Entity": "Measure"
                    }
                  },
                  "Property": "Total leadtime YCC"
                }
              },
              "queryRef": "Measure.Total leadtime YCC",
              "nativeQueryRef": "Total leadtime YCC",
              "displayName": "Total leadtime YCC"
            }
          ],
          "fieldParameters": [
            {
              "parameterExpr": {
                "Column": {
                  "Expression": {
                    "SourceRef": {
                      "Entity": "Parameter 2"
                    }
                  },
                  "Property": "Parameter"
                }
              },
              "index": 0,
              "length": 1
            }
          ]
        }
      }
    },
    "expansionStates": [
      {
        "roles": [
          "Rows"
        ],
        "levels": [
          {
            "queryRefs": [
              "D_Region.Miền"
            ],
            "isCollapsed": true,
            "identityKeys": [
              {
                "Column": {
                  "Expression": {
                    "SourceRef": {
                      "Entity": "D_Region"
                    }
                  },
                  "Property": "Miền"
                }
              }
            ],
            "isPinned": true
          },
          {
            "queryRefs": [
              "F_Ycdc.Khu vực"
            ],
            "isCollapsed": true,
            "identityKeys": [
              {
                "Column": {
                  "Expression": {
                    "SourceRef": {
                      "Entity": "F_Ycdc"
                    }
                  },
                  "Property": "Khu vực"
                }
              }
            ],
            "isPinned": true
          },
          {
            "queryRefs": [
              "F_Ycdc.DC_Type"
            ],
            "isCollapsed": true,
            "isPinned": true
          }
        ],
        "root": {
          "children": [
            {
              "identityValues": [
                {
                  "Literal": {
                    "Value": "'Miền Nam'"
                  }
                }
              ],
              "isToggled": true,
              "children": [
                {
                  "identityValues": [
                    {
                      "Literal": {
                        "Value": "'Tỉnh - Tỉnh'"
                      }
                    }
                  ],
                  "isToggled": true
                }
              ]
            },
            {
              "identityValues": [
                {
                  "Literal": {
                    "Value": "'Miền Bắc'"
                  }
                }
              ],
              "isToggled": true,
              "children": [
                {
                  "identityValues": [
                    {
                      "Literal": {
                        "Value": "'Tỉnh - Tỉnh'"
                      }
                    }
                  ],
                  "isToggled": true
                }
              ]
            }
          ]
        }
      }
    ],
    "objects": {
      "rowHeaders": [
        {
          "properties": {
            "backColor": {
              "solid": {
                "color": {
                  "expr": {
                    "ThemeDataColor": {
                      "ColorId": 0,
                      "Percent": 0
                    }
                  }
                }
              }
            },
            "fontColor": {
              "solid": {
                "color": {
                  "expr": {
                    "ThemeDataColor": {
                      "ColorId": 2,
                      "Percent": -0.25
                    }
                  }
                }
              }
            },
            "fontSize": {
              "expr": {
                "Literal": {
                  "Value": "11D"
                }
              }
            }
          }
        }
      ],
      "columnHeaders": [
        {
          "properties": {
            "backColor": {
              "solid": {
                "color": {
                  "expr": {
                    "ThemeDataColor": {
                      "ColorId": 2,
                      "Percent": 0
                    }
                  }
                }
              }
            },
            "fontColor": {
              "solid": {
                "color": {
                  "expr": {
                    "ThemeDataColor": {
                      "ColorId": 0,
                      "Percent": 0
                    }
                  }
                }
              }
            },
            "bold": {
              "expr": {
                "Literal": {
                  "Value": "true"
                }
              }
            },
            "fontSize": {
              "expr": {
                "Literal": {
                  "Value": "10.2D"
                }
              }
            }
          }
        }
      ],
      "subTotals": [
        {
          "properties": {
            "fontColor": {
              "solid": {
                "color": {
                  "expr": {
                    "Literal": {
                      "Value": "'#298c8c'"
                    }
                  }
                }
              }
            },
            "backColor": {
              "solid": {
                "color": {
                  "expr": {
                    "ThemeDataColor": {
                      "ColorId": 0,
                      "Percent": 0
                    }
                  }
                }
              }
            }
          },
          "selector": {
            "id": "Column"
          }
        },
        {
          "properties": {
            "fontColor": {
              "solid": {
                "color": {
                  "expr": {
                    "ThemeDataColor": {
                      "ColorId": 2,
                      "Percent": -0.25
                    }
                  }
                }
              }
            },
            "backColor": {
              "solid": {
                "color": {
                  "expr": {
                    "ThemeDataColor": {
                      "ColorId": 0,
                      "Percent": 0
                    }
                  }
                }
              }
            },
            "bold": {
              "expr": {
                "Literal": {
                  "Value": "true"
                }
              }
            },
            "applyToHeaders": {
              "expr": {
                "Literal": {
                  "Value": "true"
                }
              }
            }
          },
          "selector": {
            "id": "Row"
          }
        },
        {
          "properties": {
            "columnSubtotals": {
              "expr": {
                "Literal": {
                  "Value": "false"
                }
              }
            }
          }
        }
      ],
      "rowTotal": [
        {
          "properties": {
            "fontColor": {
              "solid": {
                "color": {
                  "expr": {
                    "ThemeDataColor": {
                      "ColorId": 0,
                      "Percent": 0
                    }
                  }
                }
              }
            },
            "backColor": {
              "solid": {
                "color": {
                  "expr": {
                    "ThemeDataColor": {
                      "ColorId": 2,
                      "Percent": 0
                    }
                  }
                }
              }
            },
            "applyToHeaders": {
              "expr": {
                "Literal": {
                  "Value": "true"
                }
              }
            }
          }
        }
      ],
      "columnTotal": [
        {
          "properties": {
            "fontColor": {
              "solid": {
                "color": {
                  "expr": {
                    "Literal": {
                      "Value": "'#1C6C6C'"
                    }
                  }
                }
              }
            },
            "backColor": {
              "solid": {
                "color": {
                  "expr": {
                    "ThemeDataColor": {
                      "ColorId": 0,
                      "Percent": 0
                    }
                  }
                }
              }
            },
            "applyToHeaders": {
              "expr": {
                "Literal": {
                  "Value": "true"
                }
              }
            }
          }
        }
      ],
      "values": [
        {
          "properties": {
            "fontSize": {
              "expr": {
                "Literal": {
                  "Value": "10.2D"
                }
              }
            },
            "backColorSecondary": {
              "solid": {
                "color": {
                  "expr": {
                    "ThemeDataColor": {
                      "ColorId": 0,
                      "Percent": 0
                    }
                  }
                }
              }
            },
            "wordWrap": {
              "expr": {
                "Literal": {
                  "Value": "false"
                }
              }
            }
          }
        },
        {
          "properties": {},
          "selector": {
            "data": [
              {
                "dataViewWildcard": {
                  "matchingOption": 1
                }
              }
            ],
            "metadata": "Measure.Tỷ trọng"
          }
        }
      ],
      "grid": [
        {
          "properties": {
            "gridHorizontal": {
              "expr": {
                "Literal": {
                  "Value": "true"
                }
              }
            },
            "outlineStyle": {
              "expr": {
                "Literal": {
                  "Value": "8D"
                }
              }
            },
            "gridVertical": {
              "expr": {
                "Literal": {
                  "Value": "true"
                }
              }
            },
            "outlineColor": {
              "solid": {
                "color": {
                  "expr": {
                    "ThemeDataColor": {
                      "ColorId": 0,
                      "Percent": -0.1
                    }
                  }
                }
              }
            },
            "rowPadding": {
              "expr": {
                "Literal": {
                  "Value": "2.5D"
                }
              }
            }
          }
        }
      ],
      "columnFormatting": [
        {
          "properties": {
            "fontColor": {
              "solid": {
                "color": {
                  "expr": {
                    "Literal": {
                      "Value": "'#ffffff'"
                    }
                  }
                }
              }
            },
            "styleSubtotals": {
              "expr": {
                "Literal": {
                  "Value": "false"
                }
              }
            },
            "styleHeader": {
              "expr": {
                "Literal": {
                  "Value": "true"
                }
              }
            },
            "styleValues": {
              "expr": {
                "Literal": {
                  "Value": "false"
                }
              }
            },
            "styleTotal": {
              "expr": {
                "Literal": {
                  "Value": "true"
                }
              }
            },
            "backColor": {
              "solid": {
                "color": {
                  "expr": {
                    "Literal": {
                      "Value": "'#307EB2'"
                    }
                  }
                }
              }
            },
            "dataBars": {
              "positiveColor": {
                "solid": {
                  "color": {
                    "expr": {
                      "Literal": {
                        "Value": "'#7BC1F0'"
                      }
                    }
                  }
                }
              },
              "negativeColor": {
                "solid": {
                  "color": {
                    "expr": {
                      "Literal": {
                        "Value": "'minColor'"
                      }
                    }
                  }
                }
              },
              "axisColor": {
                "solid": {
                  "color": {
                    "expr": {
                      "Literal": {
                        "Value": "'foreground'"
                      }
                    }
                  }
                }
              },
              "reverseDirection": {
                "expr": {
                  "Literal": {
                    "Value": "false"
                  }
                }
              },
              "hideText": {
                "expr": {
                  "Literal": {
                    "Value": "false"
                  }
                }
              },
              "totalMatchingOption": {
                "expr": {
                  "Literal": {
                    "Value": "1L"
                  }
                }
              }
            }
          },
          "selector": {
            "metadata": "Measure.Selected_% Số phiếu | % Số lượng"
          }
        },
        {
          "properties": {
            "styleSubtotals": {
              "expr": {
                "Literal": {
                  "Value": "false"
                }
              }
            },
            "styleHeader": {
              "expr": {
                "Literal": {
                  "Value": "true"
                }
              }
            },
            "styleValues": {
              "expr": {
                "Literal": {
                  "Value": "false"
                }
              }
            },
            "styleTotal": {
              "expr": {
                "Literal": {
                  "Value": "true"
                }
              }
            },
            "backColor": {
              "solid": {
                "color": {
                  "expr": {
                    "ThemeDataColor": {
                      "ColorId": 2,
                      "Percent": 0
                    }
                  }
                }
              }
            },
            "dataBars": {
              "positiveColor": {
                "solid": {
                  "color": {
                    "expr": {
                      "Literal": {
                        "Value": "'#78B3D9'"
                      }
                    }
                  }
                }
              },
              "negativeColor": {
                "solid": {
                  "color": {
                    "expr": {
                      "Literal": {
                        "Value": "'minColor'"
                      }
                    }
                  }
                }
              },
              "axisColor": {
                "solid": {
                  "color": {
                    "expr": {
                      "Literal": {
                        "Value": "'foreground'"
                      }
                    }
                  }
                }
              },
              "reverseDirection": {
                "expr": {
                  "Literal": {
                    "Value": "false"
                  }
                }
              },
              "hideText": {
                "expr": {
                  "Literal": {
                    "Value": "false"
                  }
                }
              },
              "totalMatchingOption": {
                "expr": {
                  "Literal": {
                    "Value": "1L"
                  }
                }
              }
            }
          },
          "selector": {
            "metadata": "Measure.Tỷ trọng"
          }
        }
      ]
    },
    "visualContainerObjects": {
      "title": [
        {
          "properties": {
            "show": {
              "expr": {
                "Literal": {
                  "Value": "true"
                }
              }
            },
            "text": {
              "expr": {
                "Literal": {
                  "Value": "'Chi tiết TG lập DC và TG xác nhận hàng theo Miền và Khu vực điều chuyển'"
                }
              }
            },
            "fontSize": {
              "expr": {
                "Literal": {
                  "Value": "10D"
                }
              }
            },
            "fontFamily": {
              "expr": {
                "Literal": {
                  "Value": "'''Segoe UI'', wf_segoe-ui_normal, helvetica, arial, sans-serif'"
                }
              }
            },
            "fontColor": {
              "solid": {
                "color": {
                  "expr": {
                    "ThemeDataColor": {
                      "ColorId": 2,
                      "Percent": -0.25
                    }
                  }
                }
              }
            },
            "bold": {
              "expr": {
                "Literal": {
                  "Value": "true"
                }
              }
            }
          }
        }
      ],
      "border": [
        {
          "properties": {
            "show": {
              "expr": {
                "Literal": {
                  "Value": "true"
                }
              }
            },
            "color": {
              "solid": {
                "color": {
                  "expr": {
                    "ThemeDataColor": {
                      "ColorId": 0,
                      "Percent": 0
                    }
                  }
                }
              }
            },
            "radius": {
              "expr": {
                "Literal": {
                  "Value": "5D"
                }
              }
            }
          }
        }
      ],
      "dropShadow": [
        {
          "properties": {
            "show": {
              "expr": {
                "Literal": {
                  "Value": "false"
                }
              }
            },
            "color": {
              "solid": {
                "color": {
                  "expr": {
                    "Literal": {
                      "Value": "'#298C8C'"
                    }
                  }
                }
              }
            }
          }
        }
      ]
    },
    "drillFilterOtherVisuals": true
  },
  "filterConfig": {
    "filters": [
      {
        "name": "f058e057463c453d29fa",
        "field": {
          "Measure": {
            "Expression": {
              "SourceRef": {
                "Entity": "Measure"
              }
            },
            "Property": "Active"
          }
        },
        "type": "Advanced",
        "filter": {
          "Version": 2,
          "From": [
            {
              "Name": "m",
              "Entity": "Measure",
              "Type": 0
            }
          ],
          "Where": [
            {
              "Condition": {
                "Comparison": {
                  "ComparisonKind": 0,
                  "Left": {
                    "Measure": {
                      "Expression": {
                        "SourceRef": {
                          "Source": "m"
                        }
                      },
                      "Property": "Active"
                    }
                  },
                  "Right": {
                    "Literal": {
                      "Value": "1L"
                    }
                  }
                }
              }
            }
          ]
        },
        "howCreated": "User",
        "isHiddenInViewMode": true
      },
      {
        "name": "d0ac4947665a30b28f7c",
        "field": {
          "Column": {
            "Expression": {
              "SourceRef": {
                "Entity": "D_Date"
              }
            },
            "Property": "yearMonth"
          }
        },
        "type": "Categorical"
      },
      {
        "name": "6b1ebaa0dac7a5374d7d",
        "field": {
          "Measure": {
            "Expression": {
              "SourceRef": {
                "Entity": "Measure"
              }
            },
            "Property": "Total leadtime YCC"
          }
        },
        "type": "Advanced"
      },
      {
        "name": "6a555364a2cb25ee5d15",
        "field": {
          "Column": {
            "Expression": {
              "SourceRef": {
                "Entity": "D_Region"
              }
            },
            "Property": "Miền"
          }
        },
        "type": "Categorical"
      },
      {
        "name": "5911cb1ca6b7b7c39cf9",
        "field": {
          "Column": {
            "Expression": {
              "SourceRef": {
                "Entity": "F_Ycdc"
              }
            },
            "Property": "Khu vực"
          }
        },
        "type": "Categorical"
      },
      {
        "name": "ad19879cc12a8355773c",
        "field": {
          "Column": {
            "Expression": {
              "SourceRef": {
                "Entity": "F_Ycdc"
              }
            },
            "Property": "DC_Type"
          }
        },
        "type": "Categorical"
      }
    ]
  }
}