{
  "$schema": "https://developer.microsoft.com/json-schemas/fabric/item/report/definition/visualContainer/2.8.0/schema.json",
  "name": "08bfab6ffb1faf9fe852",
  "position": {
    "x": 775.79556722787652,
    "y": 73.5519162659742,
    "z": 16000,
    "height": 73.121832402910783,
    "width": 239,
    "tabOrder": 16000
  },
  "visual": {
    "visualType": "card",
    "query": {
      "queryState": {
        "Values": {
          "projections": [
            {
              "field": {
                "Measure": {
                  "Expression": {
                    "SourceRef": {
                      "Entity": "Measure"
                    }
                  },
                  "Property": "_Slg_DH_CXL_4DayPlus"
                }
              },
              "queryRef": "Measure._Slg_DH_CXL_4DayPlus",
              "nativeQueryRef": "Slg DH ⩾4 Ngày CXL",
              "displayName": "Slg DH ⩾4 Ngày CXL"
            }
          ]
        }
      }
    },
    "objects": {
      "categoryLabels": [
        {
          "properties": {
            "fontSize": {
              "expr": {
                "Literal": {
                  "Value": "9D"
                }
              }
            },
            "bold": {
              "expr": {
                "Literal": {
                  "Value": "true"
                }
              }
            },
            "color": {
              "solid": {
                "color": {
                  "expr": {
                    "ThemeDataColor": {
                      "ColorId": 5,
                      "Percent": 0
                    }
                  }
                }
              }
            }
          }
        }
      ],
      "labels": [
        {
          "properties": {
            "fontFamily": {
              "expr": {
                "Literal": {
                  "Value": "'''Segoe UI'', wf_segoe-ui_normal, helvetica, arial, sans-serif'"
                }
              }
            },
            "fontSize": {
              "expr": {
                "Literal": {
                  "Value": "20D"
                }
              }
            },
            "bold": {
              "expr": {
                "Literal": {
                  "Value": "true"
                }
              }
            }
          }
        }
      ]
    },
    "visualContainerObjects": {
      "title": [
        {
          "properties": {
            "show": {
              "expr": {
                "Literal": {
                  "Value": "true"
                }
              }
            },
            "titleWrap": {
              "expr": {
                "Literal": {
                  "Value": "false"
                }
              }
            },
            "alignment": {
              "expr": {
                "Literal": {
                  "Value": "'left'"
                }
              }
            },
            "fontSize": {
              "expr": {
                "Literal": {
                  "Value": "9D"
                }
              }
            },
            "bold": {
              "expr": {
                "Literal": {
                  "Value": "true"
                }
              }
            },
            "fontFamily": {
              "expr": {
                "Literal": {
                  "Value": "'''Segoe UI'', wf_segoe-ui_normal, helvetica, arial, sans-serif'"
                }
              }
            }
          }
        }
      ],
      "background": [
        {
          "properties": {
            "show": {
              "expr": {
                "Literal": {
                  "Value": "true"
                }
              }
            },
            "color": {
              "solid": {
                "color": {
                  "expr": {
                    "ThemeDataColor": {
                      "ColorId": 0,
                      "Percent": 0
                    }
                  }
                }
              }
            },
            "transparency": {
              "expr": {
                "Literal": {
                  "Value": "0D"
                }
              }
            }
          }
        }
      ],
      "border": [
        {
          "properties": {
            "show": {
              "expr": {
                "Literal": {
                  "Value": "true"
                }
              }
            },
            "color": {
              "solid": {
                "color": {
                  "expr": {
                    "ThemeDataColor": {
                      "ColorId": 8,
                      "Percent": 0
                    }
                  }
                }
              }
            },
            "radius": {
              "expr": {
                "Literal": {
                  "Value": "3D"
                }
              }
            },
            "width": {
              "expr": {
                "Literal": {
                  "Value": "1D"
                }
              }
            }
          }
        }
      ],
      "dropShadow": [
        {
          "properties": {
            "show": {
              "expr": {
                "Literal": {
                  "Value": "true"
                }
              }
            },
            "preset": {
              "expr": {
                "Literal": {
                  "Value": "'Custom'"
                }
              }
            },
            "color": {
              "solid": {
                "color": {
                  "expr": {
                    "ThemeDataColor": {
                      "ColorId": 8,
                      "Percent": 0
                    }
                  }
                }
              }
            },
            "transparency": {
              "expr": {
                "Literal": {
                  "Value": "40D"
                }
              }
            },
            "shadowSpread": {
              "expr": {
                "Literal": {
                  "Value": "0D"
                }
              }
            },
            "shadowBlur": {
              "expr": {
                "Literal": {
                  "Value": "5D"
                }
              }
            },
            "angle": {
              "expr": {
                "Literal": {
                  "Value": "20D"
                }
              }
            },
            "shadowDistance": {
              "expr": {
                "Literal": {
                  "Value": "0D"
                }
              }
            }
          }
        }
      ],
      "stylePreset": [
        {
          "properties": {
            "name": {
              "expr": {
                "Literal": {
                  "Value": "'Minimal'"
                }
              }
            }
          }
        }
      ]
    },
    "drillFilterOtherVisuals": true
  }
}