{
  "$schema": "https://developer.microsoft.com/json-schemas/fabric/item/report/definition/visualContainer/2.6.0/schema.json",
  "name": "d5b4ac4d8ab1393a269d",
  "position": {
    "x": 9.4744633604737238,
    "y": 506.88378978534422,
    "z": 8000,
    "height": 201.8060695780903,
    "width": 421.61361954108071,
    "tabOrder": 8000
  },
  "visual": {
    "visualType": "columnChart",
    "query": {
      "queryState": {
        "Category": {
          "projections": [
            {
              "field": {
                "Column": {
                  "Expression": {
                    "SourceRef": {
                      "Entity": "FACT_NPS_SHOP"
                    }
                  },
                  "Property": "SizeShop"
                }
              },
              "queryRef": "FACT_NPS_SHOP.SizeShop",
              "nativeQueryRef": "SizeShop",
              "active": true
            }
          ]
        },
        "Y": {
          "projections": [
            {
              "field": {
                "Measure": {
                  "Expression": {
                    "SourceRef": {
                      "Entity": "_Measure"
                    }
                  },
                  "Property": "Số cửa hàng đạt %Vi phạm"
                }
              },
              "queryRef": "Measure.Số cửa hàng đạt %Lỗi đúng",
              "nativeQueryRef": "Đạt",
              "displayName": "Đạt"
            },
            {
              "field": {
                "Measure": {
                  "Expression": {
                    "SourceRef": {
                      "Entity": "_Measure"
                    }
                  },
                  "Property": "Số cửa hàng ko đạt %Vi phạm"
                }
              },
              "queryRef": "Measure.Số cửa hàng ko đạt %Lỗi đúng",
              "nativeQueryRef": "Không đạt",
              "displayName": "Không đạt"
            }
          ]
        }
      },
      "sortDefinition": {
        "sort": [
          {
            "field": {
              "Column": {
                "Expression": {
                  "SourceRef": {
                    "Entity": "FACT_NPS_SHOP"
                  }
                },
                "Property": "SizeShop"
              }
            },
            "direction": "Ascending"
          }
        ]
      }
    },
    "objects": {
      "legend": [
        {
          "properties": {
            "show": {
              "expr": {
                "Literal": {
                  "Value": "false"
                }
              }
            }
          }
        }
      ],
      "dataPoint": [
        {
          "properties": {
            "fill": {
              "solid": {
                "color": {
                  "expr": {
                    "ThemeDataColor": {
                      "ColorId": 4,
                      "Percent": 0.4
                    }
                  }
                }
              }
            }
          },
          "selector": {
            "metadata": "Measure.Số quản lý không đạt S-Star"
          }
        },
        {
          "properties": {
            "fill": {
              "solid": {
                "color": {
                  "expr": {
                    "ThemeDataColor": {
                      "ColorId": 4,
                      "Percent": 0.4
                    }
                  }
                }
              }
            }
          },
          "selector": {
            "metadata": "Measure.Số quản lý không đạt NPS"
          }
        },
        {
          "properties": {
            "fill": {
              "solid": {
                "color": {
                  "expr": {
                    "Literal": {
                      "Value": "'#DF9797'"
                    }
                  }
                }
              }
            }
          },
          "selector": {
            "metadata": "Measure.Số cửa hàng không đạt Dso"
          }
        }
      ],
      "labels": [
        {
          "properties": {
            "fontSize": {
              "expr": {
                "Literal": {
                  "Value": "8D"
                }
              }
            },
            "bold": {
              "expr": {
                "Literal": {
                  "Value": "false"
                }
              }
            },
            "show": {
              "expr": {
                "Literal": {
                  "Value": "true"
                }
              }
            },
            "labelPosition": {
              "expr": {
                "Literal": {
                  "Value": "'Auto'"
                }
              }
            },
            "labelOverflow": {
              "expr": {
                "Literal": {
                  "Value": "false"
                }
              }
            },
            "optimizeLabelDisplay": {
              "expr": {
                "Literal": {
                  "Value": "false"
                }
              }
            },
            "labelOrientation": {
              "expr": {
                "Literal": {
                  "Value": "1D"
                }
              }
            },
            "enableTitleDataLabel": {
              "expr": {
                "Literal": {
                  "Value": "false"
                }
              }
            },
            "enableDetailDataLabel": {
              "expr": {
                "Literal": {
                  "Value": "false"
                }
              }
            },
            "enableBackground": {
              "expr": {
                "Literal": {
                  "Value": "true"
                }
              }
            }
          }
        }
      ],
      "categoryAxis": [
        {
          "properties": {
            "showAxisTitle": {
              "expr": {
                "Literal": {
                  "Value": "false"
                }
              }
            }
          }
        }
      ],
      "valueAxis": [
        {
          "properties": {
            "showAxisTitle": {
              "expr": {
                "Literal": {
                  "Value": "false"
                }
              }
            },
            "show": {
              "expr": {
                "Literal": {
                  "Value": "false"
                }
              }
            }
          }
        }
      ]
    },
    "visualContainerObjects": {
      "title": [
        {
          "properties": {
            "titleWrap": {
              "expr": {
                "Literal": {
                  "Value": "true"
                }
              }
            },
            "fontSize": {
              "expr": {
                "Literal": {
                  "Value": "9D"
                }
              }
            },
            "bold": {
              "expr": {
                "Literal": {
                  "Value": "true"
                }
              }
            },
            "text": {
              "expr": {
                "Literal": {
                  "Value": "'Đánh giá %Vi phạm - Size Shop'"
                }
              }
            },
            "fontFamily": {
              "expr": {
                "Literal": {
                  "Value": "'''Segoe UI'', wf_segoe-ui_normal, helvetica, arial, sans-serif'"
                }
              }
            },
            "fontColor": {
              "solid": {
                "color": {
                  "expr": {
                    "ThemeDataColor": {
                      "ColorId": 1,
                      "Percent": 0
                    }
                  }
                }
              }
            }
          }
        }
      ],
      "background": [
        {
          "properties": {
            "show": {
              "expr": {
                "Literal": {
                  "Value": "true"
                }
              }
            },
            "color": {
              "solid": {
                "color": {
                  "expr": {
                    "ThemeDataColor": {
                      "ColorId": 0,
                      "Percent": 0
                    }
                  }
                }
              }
            },
            "transparency": {
              "expr": {
                "Literal": {
                  "Value": "10D"
                }
              }
            }
          }
        }
      ],
      "border": [
        {
          "properties": {
            "show": {
              "expr": {
                "Literal": {
                  "Value": "true"
                }
              }
            },
            "color": {
              "solid": {
                "color": {
                  "expr": {
                    "ThemeDataColor": {
                      "ColorId": 0,
                      "Percent": -0.1
                    }
                  }
                }
              }
            },
            "radius": {
              "expr": {
                "Literal": {
                  "Value": "12D"
                }
              }
            }
          }
        }
      ]
    },
    "drillFilterOtherVisuals": true
  }
}