{
  "$schema": "https://developer.microsoft.com/json-schemas/fabric/item/report/definition/visualContainer/2.8.0/schema.json",
  "name": "abdf93830de14a37ff72",
  "position": {
    "x": 256.25,
    "y": 1038.75,
    "z": 17000,
    "height": 271.25,
    "width": 436.25,
    "tabOrder": 16000
  },
  "visual": {
    "visualType": "lineChart",
    "query": {
      "queryState": {
        "Category": {
          "projections": [
            {
              "field": {
                "Column": {
                  "Expression": {
                    "SourceRef": {
                      "Entity": "D_Date"
                    }
                  },
                  "Property": "Date"
                }
              },
              "queryRef": "D_Date.Date",
              "nativeQueryRef": "Date",
              "active": true
            }
          ]
        },
        "Y": {
          "projections": [
            {
              "field": {
                "Measure": {
                  "Expression": {
                    "SourceRef": {
                      "Entity": "Measure"
                    }
                  },
                  "Property": "Số phiếu"
                }
              },
              "queryRef": "Measure.Số phiếu",
              "nativeQueryRef": "Số phiếu"
            }
          ]
        }
      },
      "sortDefinition": {
        "sort": [
          {
            "field": {
              "Column": {
                "Expression": {
                  "SourceRef": {
                    "Entity": "D_Date"
                  }
                },
                "Property": "Date"
              }
            },
            "direction": "Ascending"
          }
        ],
        "isDefaultSort": true
      }
    },
    "objects": {
      "labels": [
        {
          "properties": {
            "show": {
              "expr": {
                "Literal": {
                  "Value": "true"
                }
              }
            }
          }
        }
      ],
      "categoryAxis": [
        {
          "properties": {
            "gridlineShow": {
              "expr": {
                "Literal": {
                  "Value": "true"
                }
              }
            }
          }
        }
      ],
      "lineStyles": [
        {
          "properties": {
            "lineChartType": {
              "expr": {
                "Literal": {
                  "Value": "'smooth'"
                }
              }
            }
          }
        }
      ]
    },
    "drillFilterOtherVisuals": true
  }
}