{
  "$schema": "https://developer.microsoft.com/json-schemas/fabric/item/report/definition/visualContainer/2.8.0/schema.json",
  "name": "ff7c17eb3cc95099d057",
  "position": {
    "x": 219.62457337883959,
    "y": 650.42662116040958,
    "z": 10000,
    "height": 440.18771331058019,
    "width": 1051.1945392491468,
    "tabOrder": 10000
  },
  "visual": {
    "visualType": "tableEx",
    "query": {
      "queryState": {
        "Values": {
          "projections": [
            {
              "field": {
                "Column": {
                  "Expression": {
                    "SourceRef": {
                      "Entity": "DIM_Danh mục_Kho"
                    }
                  },
                  "Property": "Cửa hàng"
                }
              },
              "queryRef": "DIM_Danh mục_Kho.BranchName",
              "displayName": "Store"
            },
            {
              "field": {
                "Column": {
                  "Expression": {
                    "SourceRef": {
                      "Entity": "DIM_Danh mục_Phòng ban"
                    }
                  },
                  "Property": "size"
                }
              },
              "queryRef": "DIM_Danh mục_Phòng ban.size",
              "nativeQueryRef": "Size",
              "displayName": "Size"
            },
            {
              "field": {
                "Measure": {
                  "Expression": {
                    "SourceRef": {
                      "Entity": "Measure"
                    }
                  },
                  "Property": "Store_Total opportunities_plx"
                }
              },
              "queryRef": "Measure.Store_Total opportunities_plx",
              "nativeQueryRef": "Total Opps_PLX",
              "displayName": "Total Opps_PLX"
            },
            {
              "field": {
                "Measure": {
                  "Expression": {
                    "SourceRef": {
                      "Entity": "Measure"
                    }
                  },
                  "Property": "Store_Conversion by Opportunities_plx"
                }
              },
              "queryRef": "Measure.Store_Conversion by Opportunities_plx",
              "nativeQueryRef": "CRbO_PLX",
              "displayName": "CRbO_PLX"
            }
          ],
          "fieldParameters": [
            {
              "parameterExpr": {
                "Column": {
                  "Expression": {
                    "SourceRef": {
                      "Entity": "Parameter"
                    }
                  },
                  "Property": "Parameter"
                }
              },
              "index": 2,
              "length": 2,
              "sortDirection": "Descending"
            }
          ]
        }
      },
      "sortDefinition": {
        "sort": [
          {
            "field": {
              "Measure": {
                "Expression": {
                  "SourceRef": {
                    "Entity": "Measure"
                  }
                },
                "Property": "Store_Total opportunities_plx"
              }
            },
            "direction": "Descending"
          }
        ]
      }
    },
    "objects": {
      "grid": [
        {
          "properties": {
            "outlineColor": {
              "solid": {
                "color": {
                  "expr": {
                    "ThemeDataColor": {
                      "ColorId": 2,
                      "Percent": 0
                    }
                  }
                }
              }
            }
          }
        }
      ],
      "columnHeaders": [
        {
          "properties": {
            "backColor": {
              "solid": {
                "color": {
                  "expr": {
                    "ThemeDataColor": {
                      "ColorId": 2,
                      "Percent": 0
                    }
                  }
                }
              }
            },
            "fontColor": {
              "solid": {
                "color": {
                  "expr": {
                    "ThemeDataColor": {
                      "ColorId": 0,
                      "Percent": 0
                    }
                  }
                }
              }
            },
            "fontSize": {
              "expr": {
                "Literal": {
                  "Value": "9D"
                }
              }
            }
          }
        }
      ],
      "total": [
        {
          "properties": {
            "backColor": {
              "solid": {
                "color": {
                  "expr": {
                    "ThemeDataColor": {
                      "ColorId": 2,
                      "Percent": 0
                    }
                  }
                }
              }
            },
            "fontColor": {
              "solid": {
                "color": {
                  "expr": {
                    "ThemeDataColor": {
                      "ColorId": 0,
                      "Percent": 0
                    }
                  }
                }
              }
            }
          }
        }
      ],
      "columnFormatting": [
        {
          "properties": {
            "styleHeader": {
              "expr": {
                "Literal": {
                  "Value": "true"
                }
              }
            },
            "styleTotal": {
              "expr": {
                "Literal": {
                  "Value": "true"
                }
              }
            },
            "styleValues": {
              "expr": {
                "Literal": {
                  "Value": "false"
                }
              }
            },
            "backColor": {
              "solid": {
                "color": {
                  "expr": {
                    "Literal": {
                      "Value": "'#BC95AA'"
                    }
                  }
                }
              }
            },
            "dataBars": {
              "minValue": {
                "expr": {
                  "Literal": {
                    "Value": "0D"
                  }
                }
              },
              "maxValue": {
                "expr": {
                  "Literal": {
                    "Value": "1D"
                  }
                }
              },
              "positiveColor": {
                "solid": {
                  "color": {
                    "expr": {
                      "Literal": {
                        "Value": "'#FDDDEE'"
                      }
                    }
                  }
                }
              },
              "negativeColor": {
                "solid": {
                  "color": {
                    "expr": {
                      "Literal": {
                        "Value": "'#D2D3D5'"
                      }
                    }
                  }
                }
              },
              "axisColor": {
                "solid": {
                  "color": {
                    "expr": {
                      "Literal": {
                        "Value": "'#252423'"
                      }
                    }
                  }
                }
              },
              "reverseDirection": {
                "expr": {
                  "Literal": {
                    "Value": "false"
                  }
                }
              },
              "hideText": {
                "expr": {
                  "Literal": {
                    "Value": "false"
                  }
                }
              },
              "totalMatchingOption": {
                "expr": {
                  "Literal": {
                    "Value": "1L"
                  }
                }
              }
            }
          },
          "selector": {
            "metadata": "Measure.Store_Conversion rate"
          }
        },
        {
          "properties": {
            "backColor": {
              "solid": {
                "color": {
                  "expr": {
                    "ThemeDataColor": {
                      "ColorId": 3,
                      "Percent": -0.25
                    }
                  }
                }
              }
            },
            "styleHeader": {
              "expr": {
                "Literal": {
                  "Value": "true"
                }
              }
            },
            "styleValues": {
              "expr": {
                "Literal": {
                  "Value": "false"
                }
              }
            },
            "styleTotal": {
              "expr": {
                "Literal": {
                  "Value": "true"
                }
              }
            }
          },
          "selector": {
            "metadata": "Measure.Store_Sale per visitor"
          }
        },
        {
          "properties": {
            "styleHeader": {
              "expr": {
                "Literal": {
                  "Value": "true"
                }
              }
            },
            "styleTotal": {
              "expr": {
                "Literal": {
                  "Value": "true"
                }
              }
            },
            "styleValues": {
              "expr": {
                "Literal": {
                  "Value": "false"
                }
              }
            },
            "backColor": {
              "solid": {
                "color": {
                  "expr": {
                    "ThemeDataColor": {
                      "ColorId": 4,
                      "Percent": 0
                    }
                  }
                }
              }
            },
            "dataBars": {
              "minValue": {
                "expr": {
                  "Literal": {
                    "Value": "0D"
                  }
                }
              },
              "maxValue": {
                "expr": {
                  "Literal": {
                    "Value": "1D"
                  }
                }
              },
              "positiveColor": {
                "solid": {
                  "color": {
                    "expr": {
                      "Literal": {
                        "Value": "'#bcc4cc'"
                      }
                    }
                  }
                }
              },
              "negativeColor": {
                "solid": {
                  "color": {
                    "expr": {
                      "Literal": {
                        "Value": "'#D2D3D5'"
                      }
                    }
                  }
                }
              },
              "axisColor": {
                "solid": {
                  "color": {
                    "expr": {
                      "Literal": {
                        "Value": "'#252423'"
                      }
                    }
                  }
                }
              },
              "reverseDirection": {
                "expr": {
                  "Literal": {
                    "Value": "false"
                  }
                }
              },
              "hideText": {
                "expr": {
                  "Literal": {
                    "Value": "false"
                  }
                }
              }
            }
          },
          "selector": {
            "metadata": "Measure.Store_Interaction rate"
          }
        },
        {
          "properties": {
            "backColor": {
              "solid": {
                "color": {
                  "expr": {
                    "ThemeDataColor": {
                      "ColorId": 4,
                      "Percent": 0
                    }
                  }
                }
              }
            },
            "styleHeader": {
              "expr": {
                "Literal": {
                  "Value": "true"
                }
              }
            },
            "styleTotal": {
              "expr": {
                "Literal": {
                  "Value": "true"
                }
              }
            },
            "styleValues": {
              "expr": {
                "Literal": {
                  "Value": "false"
                }
              }
            }
          },
          "selector": {
            "metadata": "Measure.Store_Greeting rate"
          }
        },
        {
          "properties": {
            "styleHeader": {
              "expr": {
                "Literal": {
                  "Value": "true"
                }
              }
            },
            "styleTotal": {
              "expr": {
                "Literal": {
                  "Value": "true"
                }
              }
            },
            "styleValues": {
              "expr": {
                "Literal": {
                  "Value": "false"
                }
              }
            },
            "backColor": {
              "solid": {
                "color": {
                  "expr": {
                    "ThemeDataColor": {
                      "ColorId": 4,
                      "Percent": 0
                    }
                  }
                }
              }
            }
          },
          "selector": {
            "metadata": "Measure.Store_Avg Time To First Greeting"
          }
        },
        {
          "properties": {
            "styleHeader": {
              "expr": {
                "Literal": {
                  "Value": "true"
                }
              }
            },
            "styleTotal": {
              "expr": {
                "Literal": {
                  "Value": "true"
                }
              }
            },
            "styleValues": {
              "expr": {
                "Literal": {
                  "Value": "false"
                }
              }
            },
            "backColor": {
              "solid": {
                "color": {
                  "expr": {
                    "ThemeDataColor": {
                      "ColorId": 4,
                      "Percent": 0
                    }
                  }
                }
              }
            }
          },
          "selector": {
            "metadata": "Measure.Store_On Time Greeting rate"
          }
        },
        {
          "properties": {
            "styleHeader": {
              "expr": {
                "Literal": {
                  "Value": "true"
                }
              }
            },
            "styleTotal": {
              "expr": {
                "Literal": {
                  "Value": "true"
                }
              }
            },
            "styleValues": {
              "expr": {
                "Literal": {
                  "Value": "false"
                }
              }
            },
            "backColor": {
              "solid": {
                "color": {
                  "expr": {
                    "ThemeDataColor": {
                      "ColorId": 8,
                      "Percent": 0
                    }
                  }
                }
              }
            },
            "dataBars": {
              "positiveColor": {
                "solid": {
                  "color": {
                    "expr": {
                      "Literal": {
                        "Value": "'#ffaeae'"
                      }
                    }
                  }
                }
              },
              "negativeColor": {
                "solid": {
                  "color": {
                    "expr": {
                      "Literal": {
                        "Value": "'#D2D3D5'"
                      }
                    }
                  }
                }
              },
              "axisColor": {
                "solid": {
                  "color": {
                    "expr": {
                      "Literal": {
                        "Value": "'#252423'"
                      }
                    }
                  }
                }
              },
              "reverseDirection": {
                "expr": {
                  "Literal": {
                    "Value": "false"
                  }
                }
              },
              "hideText": {
                "expr": {
                  "Literal": {
                    "Value": "false"
                  }
                }
              }
            }
          },
          "selector": {
            "metadata": "Measure.Store_Total group"
          }
        },
        {
          "properties": {
            "styleHeader": {
              "expr": {
                "Literal": {
                  "Value": "true"
                }
              }
            },
            "styleTotal": {
              "expr": {
                "Literal": {
                  "Value": "true"
                }
              }
            },
            "styleValues": {
              "expr": {
                "Literal": {
                  "Value": "false"
                }
              }
            },
            "backColor": {
              "solid": {
                "color": {
                  "expr": {
                    "ThemeDataColor": {
                      "ColorId": 8,
                      "Percent": 0
                    }
                  }
                }
              }
            }
          },
          "selector": {
            "metadata": "Measure.Store_Group rate"
          }
        },
        {
          "properties": {
            "styleHeader": {
              "expr": {
                "Literal": {
                  "Value": "true"
                }
              }
            },
            "styleTotal": {
              "expr": {
                "Literal": {
                  "Value": "true"
                }
              }
            },
            "styleValues": {
              "expr": {
                "Literal": {
                  "Value": "false"
                }
              }
            },
            "backColor": {
              "solid": {
                "color": {
                  "expr": {
                    "ThemeDataColor": {
                      "ColorId": 8,
                      "Percent": 0
                    }
                  }
                }
              }
            }
          },
          "selector": {
            "metadata": "Measure.Store_Avg group size"
          }
        },
        {
          "properties": {
            "styleHeader": {
              "expr": {
                "Literal": {
                  "Value": "true"
                }
              }
            },
            "styleTotal": {
              "expr": {
                "Literal": {
                  "Value": "true"
                }
              }
            },
            "styleValues": {
              "expr": {
                "Literal": {
                  "Value": "false"
                }
              }
            },
            "backColor": {
              "solid": {
                "color": {
                  "expr": {
                    "ThemeDataColor": {
                      "ColorId": 8,
                      "Percent": 0
                    }
                  }
                }
              }
            }
          },
          "selector": {
            "metadata": "Measure.Store_Total group with kids"
          }
        },
        {
          "properties": {
            "styleHeader": {
              "expr": {
                "Literal": {
                  "Value": "true"
                }
              }
            },
            "styleTotal": {
              "expr": {
                "Literal": {
                  "Value": "true"
                }
              }
            },
            "styleValues": {
              "expr": {
                "Literal": {
                  "Value": "false"
                }
              }
            },
            "backColor": {
              "solid": {
                "color": {
                  "expr": {
                    "Literal": {
                      "Value": "'#FF7878'"
                    }
                  }
                }
              }
            }
          },
          "selector": {
            "metadata": "Measure.Store_Group with kids rate"
          }
        },
        {
          "properties": {
            "dataBars": {
              "positiveColor": {
                "solid": {
                  "color": {
                    "expr": {
                      "Literal": {
                        "Value": "'#7cc7c4'"
                      }
                    }
                  }
                }
              },
              "negativeColor": {
                "solid": {
                  "color": {
                    "expr": {
                      "Literal": {
                        "Value": "'#D2D3D5'"
                      }
                    }
                  }
                }
              },
              "axisColor": {
                "solid": {
                  "color": {
                    "expr": {
                      "Literal": {
                        "Value": "'#252423'"
                      }
                    }
                  }
                }
              },
              "reverseDirection": {
                "expr": {
                  "Literal": {
                    "Value": "false"
                  }
                }
              },
              "hideText": {
                "expr": {
                  "Literal": {
                    "Value": "false"
                  }
                }
              }
            }
          },
          "selector": {
            "metadata": "Measure.Store_Visit"
          }
        },
        {
          "properties": {
            "styleHeader": {
              "expr": {
                "Literal": {
                  "Value": "true"
                }
              }
            },
            "styleTotal": {
              "expr": {
                "Literal": {
                  "Value": "true"
                }
              }
            },
            "styleValues": {
              "expr": {
                "Literal": {
                  "Value": "false"
                }
              }
            },
            "backColor": {
              "solid": {
                "color": {
                  "expr": {
                    "Literal": {
                      "Value": "'#5880B0'"
                    }
                  }
                }
              }
            }
          },
          "selector": {
            "metadata": "Measure.Store_Sales transaction"
          }
        },
        {
          "properties": {
            "styleHeader": {
              "expr": {
                "Literal": {
                  "Value": "true"
                }
              }
            },
            "styleTotal": {
              "expr": {
                "Literal": {
                  "Value": "true"
                }
              }
            },
            "styleValues": {
              "expr": {
                "Literal": {
                  "Value": "false"
                }
              }
            },
            "backColor": {
              "solid": {
                "color": {
                  "expr": {
                    "ThemeDataColor": {
                      "ColorId": 6,
                      "Percent": 0
                    }
                  }
                }
              }
            }
          },
          "selector": {
            "metadata": "Measure.Store_ATV (Average Transaction Value)1"
          }
        },
        {
          "properties": {
            "styleHeader": {
              "expr": {
                "Literal": {
                  "Value": "true"
                }
              }
            },
            "styleTotal": {
              "expr": {
                "Literal": {
                  "Value": "true"
                }
              }
            },
            "styleValues": {
              "expr": {
                "Literal": {
                  "Value": "false"
                }
              }
            },
            "backColor": {
              "solid": {
                "color": {
                  "expr": {
                    "ThemeDataColor": {
                      "ColorId": 6,
                      "Percent": 0
                    }
                  }
                }
              }
            }
          },
          "selector": {
            "metadata": "Measure.Store_UPT (Units Per Transaction)1"
          }
        },
        {
          "properties": {
            "styleHeader": {
              "expr": {
                "Literal": {
                  "Value": "true"
                }
              }
            },
            "styleTotal": {
              "expr": {
                "Literal": {
                  "Value": "true"
                }
              }
            },
            "styleValues": {
              "expr": {
                "Literal": {
                  "Value": "false"
                }
              }
            },
            "backColor": {
              "solid": {
                "color": {
                  "expr": {
                    "ThemeDataColor": {
                      "ColorId": 6,
                      "Percent": 0
                    }
                  }
                }
              }
            }
          },
          "selector": {
            "metadata": "Measure.Store_ASP (Average Selling Price)1"
          }
        },
        {
          "properties": {
            "styleValues": {
              "expr": {
                "Literal": {
                  "Value": "false"
                }
              }
            },
            "styleTotal": {
              "expr": {
                "Literal": {
                  "Value": "true"
                }
              }
            },
            "styleHeader": {
              "expr": {
                "Literal": {
                  "Value": "true"
                }
              }
            },
            "backColor": {
              "solid": {
                "color": {
                  "expr": {
                    "Literal": {
                      "Value": "'#FF7878'"
                    }
                  }
                }
              }
            }
          },
          "selector": {
            "metadata": "Measure.Store_Total opportunities"
          }
        },
        {
          "properties": {
            "styleHeader": {
              "expr": {
                "Literal": {
                  "Value": "true"
                }
              }
            },
            "styleTotal": {
              "expr": {
                "Literal": {
                  "Value": "true"
                }
              }
            },
            "styleValues": {
              "expr": {
                "Literal": {
                  "Value": "false"
                }
              }
            },
            "backColor": {
              "solid": {
                "color": {
                  "expr": {
                    "Literal": {
                      "Value": "'#5880B0'"
                    }
                  }
                }
              }
            }
          },
          "selector": {
            "metadata": "Measure.Store_Sales transaction by phone"
          }
        },
        {
          "properties": {
            "backColor": {
              "solid": {
                "color": {
                  "expr": {
                    "Literal": {
                      "Value": "'#FF7878'"
                    }
                  }
                }
              }
            },
            "styleHeader": {
              "expr": {
                "Literal": {
                  "Value": "true"
                }
              }
            },
            "styleTotal": {
              "expr": {
                "Literal": {
                  "Value": "true"
                }
              }
            },
            "styleValues": {
              "expr": {
                "Literal": {
                  "Value": "false"
                }
              }
            }
          },
          "selector": {
            "metadata": "Measure.Store_Conversion by Opportunities"
          }
        },
        {
          "properties": {
            "backColor": {
              "solid": {
                "color": {
                  "expr": {
                    "ThemeDataColor": {
                      "ColorId": 9,
                      "Percent": 0
                    }
                  }
                }
              }
            },
            "styleHeader": {
              "expr": {
                "Literal": {
                  "Value": "true"
                }
              }
            },
            "styleTotal": {
              "expr": {
                "Literal": {
                  "Value": "true"
                }
              }
            },
            "styleValues": {
              "expr": {
                "Literal": {
                  "Value": "false"
                }
              }
            }
          },
          "selector": {
            "metadata": "Rank_Cửa hàng.Xếp hạng"
          }
        },
        {
          "properties": {
            "backColor": {
              "solid": {
                "color": {
                  "expr": {
                    "Literal": {
                      "Value": "'#005AA3'"
                    }
                  }
                }
              }
            },
            "styleValues": {
              "expr": {
                "Literal": {
                  "Value": "false"
                }
              }
            },
            "styleTotal": {
              "expr": {
                "Literal": {
                  "Value": "true"
                }
              }
            },
            "styleHeader": {
              "expr": {
                "Literal": {
                  "Value": "true"
                }
              }
            }
          },
          "selector": {
            "metadata": "Measure.Store_Target_CR"
          }
        },
        {
          "properties": {
            "styleHeader": {
              "expr": {
                "Literal": {
                  "Value": "true"
                }
              }
            },
            "styleTotal": {
              "expr": {
                "Literal": {
                  "Value": "true"
                }
              }
            },
            "styleValues": {
              "expr": {
                "Literal": {
                  "Value": "false"
                }
              }
            },
            "backColor": {
              "solid": {
                "color": {
                  "expr": {
                    "Literal": {
                      "Value": "'#005AA3'"
                    }
                  }
                }
              }
            }
          },
          "selector": {
            "metadata": "Measure.Store_Evaluation"
          }
        },
        {
          "properties": {
            "styleHeader": {
              "expr": {
                "Literal": {
                  "Value": "true"
                }
              }
            },
            "styleTotal": {
              "expr": {
                "Literal": {
                  "Value": "true"
                }
              }
            },
            "styleValues": {
              "expr": {
                "Literal": {
                  "Value": "false"
                }
              }
            },
            "backColor": {
              "solid": {
                "color": {
                  "expr": {
                    "Literal": {
                      "Value": "'#BC95AA'"
                    }
                  }
                }
              }
            }
          },
          "selector": {
            "metadata": "Measure.Store_Conversion rate final"
          }
        },
        {
          "properties": {
            "backColor": {
              "solid": {
                "color": {
                  "expr": {
                    "Literal": {
                      "Value": "'#FF7878'"
                    }
                  }
                }
              }
            },
            "styleValues": {
              "expr": {
                "Literal": {
                  "Value": "false"
                }
              }
            },
            "styleHeader": {
              "expr": {
                "Literal": {
                  "Value": "true"
                }
              }
            },
            "styleTotal": {
              "expr": {
                "Literal": {
                  "Value": "true"
                }
              }
            }
          },
          "selector": {
            "metadata": "Measure.Store_Total opportunities_plx"
          }
        },
        {
          "properties": {
            "backColor": {
              "solid": {
                "color": {
                  "expr": {
                    "Literal": {
                      "Value": "'#FF7878'"
                    }
                  }
                }
              }
            },
            "styleValues": {
              "expr": {
                "Literal": {
                  "Value": "false"
                }
              }
            },
            "styleTotal": {
              "expr": {
                "Literal": {
                  "Value": "true"
                }
              }
            },
            "styleHeader": {
              "expr": {
                "Literal": {
                  "Value": "true"
                }
              }
            }
          },
          "selector": {
            "metadata": "Measure.Store_Conversion by Opportunities_plx"
          }
        },
        {
          "properties": {
            "backColor": {
              "solid": {
                "color": {
                  "expr": {
                    "Literal": {
                      "Value": "'#5880B0'"
                    }
                  }
                }
              }
            },
            "styleValues": {
              "expr": {
                "Literal": {
                  "Value": "false"
                }
              }
            },
            "styleTotal": {
              "expr": {
                "Literal": {
                  "Value": "true"
                }
              }
            },
            "styleHeader": {
              "expr": {
                "Literal": {
                  "Value": "true"
                }
              }
            }
          },
          "selector": {
            "metadata": "Measure.Store_ATV (Average Transaction Value)"
          }
        },
        {
          "properties": {
            "backColor": {
              "solid": {
                "color": {
                  "expr": {
                    "Literal": {
                      "Value": "'#5880B0'"
                    }
                  }
                }
              }
            },
            "styleTotal": {
              "expr": {
                "Literal": {
                  "Value": "true"
                }
              }
            },
            "styleHeader": {
              "expr": {
                "Literal": {
                  "Value": "true"
                }
              }
            },
            "styleValues": {
              "expr": {
                "Literal": {
                  "Value": "false"
                }
              }
            }
          },
          "selector": {
            "metadata": "Measure.Store_UPT (Units Per Transaction)"
          }
        },
        {
          "properties": {
            "backColor": {
              "solid": {
                "color": {
                  "expr": {
                    "Literal": {
                      "Value": "'#5880B0'"
                    }
                  }
                }
              }
            },
            "styleValues": {
              "expr": {
                "Literal": {
                  "Value": "false"
                }
              }
            },
            "styleTotal": {
              "expr": {
                "Literal": {
                  "Value": "true"
                }
              }
            },
            "styleHeader": {
              "expr": {
                "Literal": {
                  "Value": "true"
                }
              }
            }
          },
          "selector": {
            "metadata": "Measure.Store_ASP (Average Selling Price)"
          }
        },
        {
          "properties": {
            "alignment": {
              "expr": {
                "Literal": {
                  "Value": "'Center'"
                }
              }
            },
            "styleTotal": {
              "expr": {
                "Literal": {
                  "Value": "true"
                }
              }
            }
          },
          "selector": {
            "metadata": "Measure.Store_Avg dwell time"
          }
        }
      ],
      "values": [
        {
          "properties": {
            "backColor": {
              "solid": {
                "color": {
                  "expr": {
                    "Conditional": {
                      "Cases": [
                        {
                          "Condition": {
                            "Comparison": {
                              "ComparisonKind": 0,
                              "Left": {
                                "Measure": {
                                  "Expression": {
                                    "SourceRef": {
                                      "Entity": "Measure"
                                    }
                                  },
                                  "Property": "Store_Evaluation"
                                }
                              },
                              "Right": {
                                "Literal": {
                                  "Value": "'Không đạt'"
                                }
                              }
                            },
                            "Annotations": {
                              "PowerBI.SQExprEvaluationKind": 1,
                              "PowerBI.SQExprTextOperatorOption": 2
                            }
                          },
                          "Value": {
                            "Literal": {
                              "Value": "'#EEB2B9'"
                            }
                          }
                        },
                        {
                          "Condition": {
                            "Comparison": {
                              "ComparisonKind": 0,
                              "Left": {
                                "Measure": {
                                  "Expression": {
                                    "SourceRef": {
                                      "Entity": "Measure"
                                    }
                                  },
                                  "Property": "Store_Evaluation"
                                }
                              },
                              "Right": {
                                "Literal": {
                                  "Value": "'Đạt'"
                                }
                              }
                            },
                            "Annotations": {
                              "PowerBI.SQExprEvaluationKind": 1,
                              "PowerBI.SQExprTextOperatorOption": 2
                            }
                          },
                          "Value": {
                            "Literal": {
                              "Value": "'#DDF1DB'"
                            }
                          }
                        }
                      ]
                    }
                  }
                }
              }
            }
          },
          "selector": {
            "data": [
              {
                "dataViewWildcard": {
                  "matchingOption": 1
                }
              }
            ],
            "metadata": "Measure.Store_Evaluation"
          }
        }
      ]
    },
    "visualContainerObjects": {
      "title": [
        {
          "properties": {
            "show": {
              "expr": {
                "Literal": {
                  "Value": "false"
                }
              }
            },
            "fontSize": {
              "expr": {
                "Literal": {
                  "Value": "10D"
                }
              }
            },
            "text": {
              "expr": {
                "Literal": {
                  "Value": "'Table_Store detail'"
                }
              }
            },
            "bold": {
              "expr": {
                "Literal": {
                  "Value": "true"
                }
              }
            }
          }
        }
      ],
      "border": [
        {
          "properties": {
            "show": {
              "expr": {
                "Literal": {
                  "Value": "true"
                }
              }
            },
            "color": {
              "solid": {
                "color": {
                  "expr": {
                    "ThemeDataColor": {
                      "ColorId": 0,
                      "Percent": 0
                    }
                  }
                }
              }
            },
            "radius": {
              "expr": {
                "Literal": {
                  "Value": "10D"
                }
              }
            }
          }
        }
      ]
    },
    "drillFilterOtherVisuals": true
  }
}